{
  "networkId": 0,
  "tokens": [
    {
      "id": "66da610efb5129c062e88e5fd65fe810f31efd1597021b2edf887a4360fa0800",
      "name": "Alf",
      "symbol": "ALF",
      "decimals": 9,
      "description": "Alf, first token deployed on the mainnet",
      "logoURI": "https://raw.githubusercontent.com/alephium/token-list/master/logos/ALF.png"
    },
    {
      "id": "b2d71c116408ae47b931482a440f675dc9ea64453db24ee931dacd578cae9002",
      "name": "ALPHpaca",
      "symbol": "PACA",
      "decimals": 0,
      "description": "Part Alpaca, part ecosystem, part coin and part meme. ALPHpaca is rapidly trying to expand it's uses across the Alephium ecosystem.",
      "logoURI": "https://raw.githubusercontent.com/alephium/token-list/master/logos/PACA.png"
    },
    {
      "id": "b522184377a33e376e997a950288fa76c1f48e97bc29cd10779adc7cfb673200",
      "name": "Berry",
      "symbol": "BERRY",
      "decimals": 0,
      "description": "Mr Berry's coin",
      "logoURI": "https://raw.githubusercontent.com/alephium/token-list/master/logos/BERRY.png"
    },
    {
      "id": "1516c410b54470d667e1315ce2faa81870c76c5c7a491e3e86eeec8366495502",
      "name": "Montycoin",
      "symbol": "TAIL",
      "decimals": 0,
      "description": "Montycoin is an incentivization token made for fun and immersion into MontaiL's DJ'ing career. With widely growing uses.",
      "logoURI": "https://raw.githubusercontent.com/alephium/token-list/master/logos/TAIL.png"
    },
    {
      "id": "1a281053ba8601a658368594da034c2e99a0fb951b86498d05e76aedfe666800",
      "name": "AYIN",
      "symbol": "AYIN",
      "decimals": 18,
      "description": "$AYIN is a DEX token, that incentivises users through fees and other mechanisms to participate in trading on Alephium",
      "logoURI": "https://raw.githubusercontent.com/alephium/token-list/master/logos/AYIN.png"
    },
    {
      "id": "5bf2f559ae714dab83ff36bed4d9e634dfda3ca9ed755d60f00be89e2a20bd00",
      "name": "Staked Ayin",
      "symbol": "XAYIN",
      "decimals": 18,
      "description": "xAyin is single-staked Ayin accumulating trading fees and additional Ayins from the DEX",
      "logoURI": "https://raw.githubusercontent.com/alephium/token-list/master/logos/XAYIN.png"
    },
    {
      "id": "7da28936499f56ffed497fe7eba856aa85eeb943bab2478e36f7020d89cd2400",
      "name": "Vlad",
      "symbol": "VLAD",
      "decimals": 9,
      "description": "Enough $VLAD entitles you to some VLAD time, at VLAD's discretion, to talk about VLAD, with VLAD in a VLAD setup of his choosing. This is the way of the VLAD. $VLAD is a valueless memexperimentcoin. NFA applies.",
      "logoURI": "https://raw.githubusercontent.com/alephium/token-list/master/logos/VLAD.png"
    },
    {
      "id": "2bc4b844502d6c27b57dfe064f95353647a606b3d92150786ecacb56c885c800",
      "name": "Jekyll",
      "symbol": "JKL",
      "decimals": 18,
      "description": "Jekyll comes to life as the sun rises...",
      "logoURI": "https://raw.githubusercontent.com/alephium/token-list/master/logos/JKL.png"
    },
    {
      "id": "19246e8c2899bc258a1156e08466e3cdd3323da756d8a543c7fc911847b96f00",
      "name": "Wrapped Ether (AlphBridge)",
      "symbol": "WETH",
      "decimals": 18,
      "description": "ETH Bridged to Alephium from Alephium Bridge",
      "logoURI": "https://raw.githubusercontent.com/alephium/token-list/master/logos/WETH.png"
    },
    {
      "id": "383bc735a4de6722af80546ec9eeb3cff508f2f68e97da19489ce69f3e703200",
      "name": "Wrapped BTC (AlphBridge)",
      "symbol": "WBTC",
      "decimals": 8,
      "description": "wBTC Bridged to Alephium from Alephium Bridge",
      "logoURI": "https://raw.githubusercontent.com/alephium/token-list/master/logos/WBTC.png"
    },
    {
      "id": "556d9582463fe44fbd108aedc9f409f69086dc78d994b88ea6c9e65f8bf98e00",
      "name": "Tether USD (AlphBridge)",
      "symbol": "USDT",
      "decimals": 6,
      "description": "USDT Bridged to Alephium from Alephium Bridge",
      "logoURI": "https://raw.githubusercontent.com/alephium/token-list/master/logos/USDT.png"
    },
    {
      "id": "722954d9067c5a5ad532746a024f2a9d7a18ed9b90e27d0a3a504962160b5600",
      "name": "USD Coin (AlphBridge)",
      "symbol": "USDC",
      "decimals": 6,
      "description": "USDC Bridged to Alephium from Alephium Bridge",
      "logoURI": "https://raw.githubusercontent.com/alephium/token-list/master/logos/USDC.png"
    },
    {
      "id": "3d0a1895108782acfa875c2829b0bf76cb586d95ffa4ea9855982667cc73b700",
      "name": "Dai Stablecoin (AlphBridge)",
      "symbol": "DAI",
      "decimals": 18,
      "description": "DAI Bridged to Alephium from Alephium Bridge",
      "logoURI": "https://raw.githubusercontent.com/alephium/token-list/master/logos/DAI.png"
    },
    {
      "id": "df3008f43a7cc1d4a37eef71bf581fc4b9c3be4e2d58ed6d1df483bbb83bd200",
      "name": "NUMBER GO UP",
      "symbol": "NGU",
      "decimals": 7,
      "description": "Number Go Up",
      "logoURI": "https://raw.githubusercontent.com/alephium/token-list/master/logos/NGU.png"
    },
    {
      "id": "11379064c747f89753d493b562130a63caf1a1fc448fcb161e507d2e542c0b00",
      "name": "VIRAL",
      "symbol": "VIRL",
      "decimals": 4,
      "description": "The most contagious token on the Alephium Blockchain.",
      "logoURI": "https://raw.githubusercontent.com/alephium/token-list/master/logos/VIRL.png"
    },
    {
      "id": "130f008dcc71ad5138bdae00d918acef3b78ddbe95e627215a36a47b6b151100",
      "name": "BUBBLE",
      "symbol": "BUBBLE",
      "decimals": 9,
      "description": "Governance token for the AlphDolphins NFT Collections",
      "logoURI": "https://raw.githubusercontent.com/alephium/token-list/master/logos/BUBBLE.png"
    },
    {
      "id": "7dd0c01b2c835ed659c85c1ae64c7c10b916c06f13cf5b91f1369a5a3feda000",
      "name": "CYXE",
      "symbol": "CYXE",
      "decimals": 4,
      "description": "Your Memory. Your Eyes. Your Life.",
      "logoURI": "https://raw.githubusercontent.com/alephium/token-list/master/logos/CYXE.png"
    },
    {
      "id": "c1aeea313e36454f35beaf40130c9219faa40ba645aff93e16429146039f8202",
      "name": "Wang",
      "symbol": "WANG",
      "decimals": 5,
      "description": "The first mystical coin, endowing its holders with the spirit of Alephium.",
      "logoURI": "https://raw.githubusercontent.com/alephium/token-list/master/logos/WANG.png"
    },
    {
      "id": "4e0eb20afb173cd534ae29acd013861115482c1e3d8ed626294bbe1008a3f900",
      "name": "KleoMixer",
      "symbol": "MIX",
      "decimals": 8,
      "description": "$MIX is the native token of the KleoMixer platform",
      "logoURI": "https://raw.githubusercontent.com/alephium/token-list/master/logos/MIX.png"
    },
    {
      "id": "93cc555d3dfc0a81aa6f3127c0108e529a32c87c595c1b89f1855e698c2bc700",
      "name": "SUCC",
      "symbol": "SUCC",
      "decimals": 10,
      "description": "Tribute to Sir Moist. 1 alph = 1 SUCC",
      "logoURI": "https://raw.githubusercontent.com/alephium/token-list/master/logos/SUCC.png"
     }
    
  ]
}
